sterm/__init__.py
sterm/cli.py
sterm/terminal.py
sterm/uart.py
sterm-6.0.3.data/data/man/man1/sterm.1
sterm-6.0.3.dist-info/LICENSE
sterm-6.0.3.dist-info/METADATA
sterm-6.0.3.dist-info/WHEEL
sterm-6.0.3.dist-info/entry_points.txt
sterm-6.0.3.dist-info/top_level.txt
sterm-6.0.3.dist-info/RECORD
