Metadata-Version: 2.1
Name: sterm
Version: 6.0.3
Summary: A minimal serial / UART command line terminal that focus on being easy to use.
Home-page: https://github.com/rstemmer/sterm
Author: Ralf Stemmer
Author-email: ralf.stemmer@gmx.net
License: GPL
Project-URL: Documentation, https://github.com/rstemmer/sterm
Project-URL: Source, https://github.com/rstemmer/sterm
Project-URL: Tracker, https://github.com/rstemmer/sterm/issues
Keywords: serial-communication serial-terminal terminal uart rs232 monitoring tty pyserial serial
Classifier: Programming Language :: Python :: 3
Classifier: Programming Language :: Python :: 3.8
Classifier: Programming Language :: Python :: 3.9
Classifier: Programming Language :: Python :: 3.10
Classifier: Programming Language :: Python :: 3.11
Classifier: Programming Language :: Python :: 3.12
Classifier: Development Status :: 5 - Production/Stable
Classifier: License :: OSI Approved :: GNU General Public License v3 (GPLv3)
Classifier: Operating System :: POSIX :: Linux
Classifier: Environment :: Console
Classifier: Intended Audience :: End Users/Desktop
Classifier: Intended Audience :: Developers
Classifier: Intended Audience :: System Administrators
Classifier: Intended Audience :: Education
Classifier: Intended Audience :: Science/Research
Classifier: Topic :: Terminals
Classifier: Topic :: Terminals :: Serial
Classifier: Topic :: Communications
Classifier: Topic :: Scientific/Engineering
Classifier: Topic :: Software Development :: Debuggers
Classifier: Topic :: Software Development :: Embedded Systems
Classifier: Topic :: System :: Logging
Classifier: Topic :: System :: Monitoring
Classifier: Topic :: Utilities
Requires-Python: >=3.8
License-File: LICENSE
Requires-Dist: pyserial
